pyuvdata/__init__.py
pyuvdata/analytic_beam.py
pyuvdata/beam_interface.py
pyuvdata/datasets.py
pyuvdata/docstrings.py
pyuvdata/parameter.py
pyuvdata/telescopes.py
pyuvdata/uvbase.py
pyuvdata/data/README.md
pyuvdata/data/__init__.py
pyuvdata/data/hera_ant_pos.csv
pyuvdata/data/jpl_major_bodies.json
pyuvdata/data/mwa128_ant_layouts.npz
pyuvdata/data/mwa_ant_pos.csv
pyuvdata/data/test_analytic_beam.py
pyuvdata/data/test_data.yaml
pyuvdata/data/test_data_registry.txt
pyuvdata/data/mwa_config_data/Chebychev_coeff.h5
pyuvdata/data/mwa_config_data/MWA_rev_cb_10khz_doubles.h5
pyuvdata/data/mwa_config_data/MWA_rev_cb_10khz_doubles.txt
pyuvdata/data/mwa_config_data/mwax_pfb_bandpass_40kHz.h5
pyuvdata/data/mwa_config_data/mwax_pfb_bandpass_80kHz.h5
pyuvdata/data/mwa_config_data/sigma1.h5
pyuvdata/testing/__init__.py
pyuvdata/testing/warning_check.py
pyuvdata/utils/__init__.py
pyuvdata/utils/_coordinates.cpython-312-x86_64-linux-gnu.so
pyuvdata/utils/_phasing.cpython-312-x86_64-linux-gnu.so
pyuvdata/utils/antenna.py
pyuvdata/utils/apply_uvflag.py
pyuvdata/utils/array_collapse.py
pyuvdata/utils/bls.py
pyuvdata/utils/bls_numba.py
pyuvdata/utils/bltaxis.py
pyuvdata/utils/coordinates.c
pyuvdata/utils/coordinates.py
pyuvdata/utils/coordinates.pyx
pyuvdata/utils/frequency.py
pyuvdata/utils/history.py
pyuvdata/utils/phase_center_catalog.py
pyuvdata/utils/phasing.c
pyuvdata/utils/phasing.py
pyuvdata/utils/phasing.pyx
pyuvdata/utils/plotting.py
pyuvdata/utils/pol.py
pyuvdata/utils/redundancy.py
pyuvdata/utils/times.py
pyuvdata/utils/tools.py
pyuvdata/utils/types.py
pyuvdata/utils/uvcalibrate.py
pyuvdata/utils/io/__init__.py
pyuvdata/utils/io/antpos.py
pyuvdata/utils/io/fhd.py
pyuvdata/utils/io/fits.py
pyuvdata/utils/io/hdf5.py
pyuvdata/utils/io/ms.py
pyuvdata/uvbeam/__init__.py
pyuvdata/uvbeam/_uvbeam.cpython-312-x86_64-linux-gnu.so
pyuvdata/uvbeam/beamfits.py
pyuvdata/uvbeam/cst_beam.py
pyuvdata/uvbeam/feko_beam.py
pyuvdata-3.2.5.dist-info/METADATA
pyuvdata-3.2.5.dist-info/WHEEL
pyuvdata-3.2.5.dist-info/top_level.txt
pyuvdata-3.2.5.dist-info/RECORD
pyuvdata-3.2.5.dist-info/licenses/LICENSE
pyuvdata-3.2.5.dist-info/sboms/auditwheel.cdx.json
