Metadata-Version: 2.4
Name: pyuvdata
Version: 3.2.5
Summary: A pythonic interface for radio astronomy interferometry data
Author-email: Bryna Hazelton <brynah@phys.washington.edu>, Adam Beardsley <adam.beardsley@winona.edu>, Daniel Jacobs <daniel.c.jacobs@gmail.com>, Garrett Keating <garrett.keating@cfa.harvard.edu>, Nicholas Kern <nkern@mit.edu>, Matthew Kolopanis <matthew.kolopanis@gmail.com>, Adam Lanman <alanman@mit.edu>, Paul La Plante <paul.laplante@unlv.edu>, Steven Murray <murray.steveng@gmail.com>, Jonathan Pober <jonathan_pober@brown.edu>, Pyxie Star <pyxiestar@gmail.com>
Maintainer-email: Bryna Hazelton <brynah@phys.washington.edu>, Matthew Kolopanis <matthew.kolopanis@gmail.com>, Garrett Keating <garrett.keating@cfa.harvard.edu>, Steven Murray <murray.steveng@gmail.com>
Project-URL: Repository, https://github.com/RadioAstronomySoftwareGroup/pyuvdata
Project-URL: Documentation, https://pyuvdata.readthedocs.io
Keywords: radio astronomy,interferometry
Classifier: License :: OSI Approved :: BSD License
Classifier: Development Status :: 5 - Production/Stable
Classifier: Intended Audience :: Science/Research
Classifier: Programming Language :: Python :: 3.11
Classifier: Programming Language :: Python :: 3.12
Classifier: Programming Language :: Python :: 3.13
Classifier: Topic :: Scientific/Engineering :: Astronomy
Requires-Python: >=3.11
License-File: LICENSE
Requires-Dist: astropy>=6.0
Requires-Dist: docstring-parser>=0.15
Requires-Dist: h5py>=3.7
Requires-Dist: numba<0.63,>=0.57.0
Requires-Dist: numpy>=1.23
Requires-Dist: pyerfa>=2.0.1.1
Requires-Dist: pyyaml>=5.4.1
Requires-Dist: scipy>=1.9
Requires-Dist: setuptools_scm>=8.1
Provides-Extra: astroquery
Requires-Dist: astroquery>=0.4.4; extra == "astroquery"
Provides-Extra: casa
Requires-Dist: python-casacore>=3.5.2; extra == "casa"
Requires-Dist: numpy<2.0,>=1.23; extra == "casa"
Provides-Extra: hdf5-compression
Requires-Dist: hdf5plugin>=3.3.1; extra == "hdf5-compression"
Provides-Extra: healpix
Requires-Dist: astropy_healpix>=1.0.2; extra == "healpix"
Provides-Extra: lunar
Requires-Dist: lunarsky>=0.2.5; extra == "lunar"
Provides-Extra: novas
Requires-Dist: novas; extra == "novas"
Requires-Dist: novas_de405; extra == "novas"
Provides-Extra: plotting
Requires-Dist: matplotlib>=3.7; extra == "plotting"
Provides-Extra: all
Requires-Dist: pyuvdata[astroquery,casa,hdf5_compression,healpix,lunar,novas,plotting]; extra == "all"
Provides-Extra: tutorial
Requires-Dist: pyuvdata[plotting]; extra == "tutorial"
Requires-Dist: pooch>=1.8; extra == "tutorial"
Provides-Extra: test
Requires-Dist: coverage; extra == "test"
Requires-Dist: cython>=3.0; extra == "test"
Requires-Dist: pooch>=1.8; extra == "test"
Requires-Dist: pre-commit; extra == "test"
Requires-Dist: pytest>=8.2.0; extra == "test"
Requires-Dist: pytest-xdist; extra == "test"
Requires-Dist: pytest-cases>=3.9.1; extra == "test"
Requires-Dist: pytest-cov; extra == "test"
Requires-Dist: sybil>=8.0; extra == "test"
Provides-Extra: doc
Requires-Dist: pyuvdata[tutorial]; extra == "doc"
Requires-Dist: pypandoc; extra == "doc"
Requires-Dist: sphinx; extra == "doc"
Provides-Extra: dev
Requires-Dist: pyuvdata[all,doc,test]; extra == "dev"
Dynamic: license-file
